whackerhero.py
whackerhero-0.1.1.dist-info/LICENSE.txt
whackerhero-0.1.1.dist-info/METADATA
whackerhero-0.1.1.dist-info/WHEEL
whackerhero-0.1.1.dist-info/entry_points.txt
whackerhero-0.1.1.dist-info/top_level.txt
whackerhero-0.1.1.dist-info/RECORD
