Metadata-Version: 2.1
Name: whackerhero
Version: 0.1.1
Summary: Generate Boomwhacker play-along videos from MIDI files
Home-page: https://github.com/allejok96/whackerhero
Author: allejok96
Keywords: boomwhacker video generator midi piano-roll
Classifier: Development Status :: 3 - Alpha
Classifier: Intended Audience :: Education
Classifier: Intended Audience :: End Users/Desktop
Classifier: License :: OSI Approved :: GNU General Public License v3 (GPLv3)
Classifier: Programming Language :: Python :: 3.7
Classifier: Programming Language :: Python :: 3.8
Classifier: Programming Language :: Python :: 3.9
Classifier: Programming Language :: Python :: 3.10
Classifier: Topic :: Games/Entertainment
Classifier: Topic :: Multimedia :: Sound/Audio :: MIDI
Classifier: Topic :: Multimedia :: Video
Requires-Python: >=3.7
License-File: LICENSE.txt
Requires-Dist: mido
Requires-Dist: moviepy
Requires-Dist: pillow
Provides-Extra: gui
Requires-Dist: Gooey ; extra == 'gui'
